README.rst
setup.py
bin/check-phedex
bin/consistency-dump-tree
bin/consistency-invalidate
bin/consistency-web-install
bin/dynamo-consistency
bin/set-status
dynamo_consistency/__init__.py
dynamo_consistency/_version.py
dynamo_consistency/cache.py
dynamo_consistency/config.py
dynamo_consistency/consistency_config.json
dynamo_consistency/create.py
dynamo_consistency/datatypes.py
dynamo_consistency/emptyremover.py
dynamo_consistency/filters.py
dynamo_consistency/history.py
dynamo_consistency/inventorylister.py
dynamo_consistency/lock.py
dynamo_consistency/logsetup.py
dynamo_consistency/main.py
dynamo_consistency/messaging.py
dynamo_consistency/parser.py
dynamo_consistency/picker.py
dynamo_consistency/remotelister.py
dynamo_consistency/report_schema.sql
dynamo_consistency/signaling.py
dynamo_consistency/summary.py
dynamo_consistency.egg-info/PKG-INFO
dynamo_consistency.egg-info/SOURCES.txt
dynamo_consistency.egg-info/dependency_links.txt
dynamo_consistency.egg-info/requires.txt
dynamo_consistency.egg-info/top_level.txt
dynamo_consistency/backend/__init__.py
dynamo_consistency/backend/filereader.py
dynamo_consistency/backend/listers.py
dynamo_consistency/backend/prod.py
dynamo_consistency/backend/redirectors.py
dynamo_consistency/backend/test.py
dynamo_consistency/cms/__init__.py
dynamo_consistency/cms/checkphedex.py
dynamo_consistency/cms/filedumps.py
dynamo_consistency/cms/filters.py
dynamo_consistency/cms/unmerged.py
dynamo_consistency/dynamo/__init__.py
dynamo_consistency/dynamo/v1/__init__.py
dynamo_consistency/dynamo/v1/inventory.py
dynamo_consistency/dynamo/v1/mysql.py
dynamo_consistency/dynamo/v1/registry.py
dynamo_consistency/dynamo/v1/siteinfo.py
dynamo_consistency/dynamo/v2/__init__.py
dynamo_consistency/dynamo/v2/inventory.py
dynamo_consistency/dynamo/v2/registry.py
dynamo_consistency/dynamo/v2/siteinfo.py
dynamo_consistency/web/dynamo.css
dynamo_consistency/web/explanations.rst
dynamo_consistency/web/files.txt
dynamo_consistency/web/index.php
dynamo_consistency/web/maketables.sql
dynamo_consistency/web/output.html
dynamo_consistency/web/sorttable.js
dynamo_consistency/web/stylin.css
test/test_addfiles.py
test/test_config.py
test/test_datatypes.py
