Metadata-Version: 1.2
Name: dynamo-consistency
Version: 2.11.1
Summary: Consistency plugin for Dynamo Dynamic Data Management System
Home-page: https://github.com/SmartDataProjects/dynamo-consistency
Author: Daniel Abercrombie
Author-email: dabercro@mit.edu
License: UNKNOWN
Platform: UNKNOWN
Requires-Python: >=2.6, <3
